nr/__init__.py
nr/databind/__init__.py
nr/databind/rest/__init__.py
nr/databind/rest/flask.py
nr/databind/rest/requests_client.py
nr.databind.rest-0.0.3.dist-info/LICENSE.txt
nr.databind.rest-0.0.3.dist-info/METADATA
nr.databind.rest-0.0.3.dist-info/WHEEL
nr.databind.rest-0.0.3.dist-info/top_level.txt
nr.databind.rest-0.0.3.dist-info/zip-safe
nr.databind.rest-0.0.3.dist-info/RECORD
