Metadata-Version: 2.1
Name: nr.databind.rest
Version: 0.0.3
Summary: Package description here.
Home-page: https://git.niklasrosenstein.com/NiklasRosenstein/nr
Author: Niklas Rosenstein
Author-email: rosensteinniklas@gmail.com
License: MIT
Platform: UNKNOWN
Requires-Python: >=3.4.0,<4.0.0
Requires-Dist: nr.collections (<1.0.0,>=0.1.0)
Requires-Dist: nr.interface (<1.0.0,>=0.0.2)
Requires-Dist: nr.databind.core (<0.1.0,>=0.0.5)
Requires-Dist: nr.databind.json (<0.1.0,>=0.0.5)
Requires-Dist: nr.metaclass (<0.1.0,>=0.0.5)
Requires-Dist: nr.pylang.utils (<0.1.0,>=0.0.1)
Requires-Dist: nr.sumtype (<0.1.0,>=0.0.2)
